radiochart/__init__.py
radiochart/chart.py
radiochart/cli.py
radiochart-0.5.1.dist-info/METADATA
radiochart-0.5.1.dist-info/WHEEL
radiochart-0.5.1.dist-info/entry_points.txt
radiochart-0.5.1.dist-info/top_level.txt
radiochart-0.5.1.dist-info/RECORD
