Metadata-Version: 2.4
Name: radiochart
Version: 0.5.1
Summary: CLI tool to generate Arma 3 radio frequency hierarchy charts
Home-page: https://github.com/kingcharlesvi/radiochart
Author: KingCharlesVII
Author-email: KingCharlesVII <viikingcharles@gmail.com>
License: MIT
Requires-Python: >=3.7
Requires-Dist: graphviz
Dynamic: author
Dynamic: home-page
Dynamic: requires-python
